notemodel/__init__.py
notemodel/database/__init__.py
notemodel/database/core.py
notemodel/models/__init__.py
notemodel/models/yolo.py
notemodel/util/__init__.py
notemodel/util/core.py
notemodel-0.1.0.dist-info/METADATA
notemodel-0.1.0.dist-info/WHEEL
notemodel-0.1.0.dist-info/top_level.txt
notemodel-0.1.0.dist-info/RECORD
