Metadata-Version: 2.1
Name: notemodel
Version: 0.1.0
Summary: notemodel
Home-page: https://github.com/1007530194
Author: niuliangtao
Author-email: 1007530194@qq.com
License: UNKNOWN
Platform: UNKNOWN
Requires-Dist: numpy
